shell_retry
