Metadata-Version: 1.0
Name: shell-retry
Version: 0.0.7
Summary: Wrapper for call any utilities with retries until they succeed
Home-page: https://github.com/strizhechenko/shell-retry
Author: Oleg Strizhechenko
Author-email: oleg.strizhechenko@gmail.com
License: MIT
Platform: UNKNOWN
